README.md
setup.cfg
setup.py
django_recipes.egg-info/PKG-INFO
django_recipes.egg-info/SOURCES.txt
django_recipes.egg-info/dependency_links.txt
django_recipes.egg-info/top_level.txt
recipes_app/__init__.py
recipes_app/admin.py
recipes_app/apps.py
recipes_app/models.py
recipes_app/serializers.py
recipes_app/tests_integration.py
recipes_app/tests_unit.py
recipes_app/urls.py
recipes_app/views.py
recipes_app/migrations/0001_initial.py
recipes_app/migrations/__init__.py
recipes_django/__init__.py
recipes_django/asgi.py
recipes_django/settings.py
recipes_django/urls.py
recipes_django/views.py
recipes_django/wsgi.py