Metadata-Version: 2.1
Name: django-recipes
Version: 0.0.15
Summary: A Django app for your recipes.
Author: Davide Borgonovo - Fabio Villa
License: MIT  # Example license
Classifier: Environment :: Web Environment
Classifier: Framework :: Django :: 4.1
Classifier: Intended Audience :: Developers
Classifier: Operating System :: OS Independent
Classifier: Programming Language :: Python
Classifier: Programming Language :: Python :: 3
Classifier: Programming Language :: Python :: 3 :: Only
Classifier: Programming Language :: Python :: 3.6
Classifier: Programming Language :: Python :: 3.7
Classifier: Programming Language :: Python :: 3.8
Classifier: Programming Language :: Python :: 3.9
Classifier: Programming Language :: Python :: 3.10
